jobo_scraper/__init__.py
jobo_scraper/logging_messages.py
jobo_scraper/scraper.py
jobo_scraper-1.0.2.dist-info/LICENSE
jobo_scraper-1.0.2.dist-info/WHEEL
jobo_scraper-1.0.2.dist-info/METADATA
jobo_scraper-1.0.2.dist-info/RECORD
